Shared Butterfly FFT/Top_FFT/butterfly_dit.v
`timescale 1ns/1ps

module butterfly_dit #(
    parameter DATA_WIDTH   = 16,
    parameter FACTOR_WIDTH = 16,
    parameter FRAC_BITS    = 14
)(
    input  wire                           clk,
    input  wire                           rst,
    input  wire [2*DATA_WIDTH-1:0]        in_x0,
    input  wire [2*DATA_WIDTH-1:0]        in_x1,
    input  wire [2*FACTOR_WIDTH-1:0]      w,
    output reg  [2*DATA_WIDTH-1:0]        out_x0,
    output reg  [2*DATA_WIDTH-1:0]        out_x1
);
    wire signed [DATA_WIDTH-1:0] x0_r = in_x0[2*DATA_WIDTH-1:DATA_WIDTH];
    wire signed [DATA_WIDTH-1:0] x0_i = in_x0[DATA_WIDTH-1:0];
    wire signed [DATA_WIDTH-1:0] x1_r = in_x1[2*DATA_WIDTH-1:DATA_WIDTH];
    wire signed [DATA_WIDTH-1:0] x1_i = in_x1[DATA_WIDTH-1:0];

    wire signed [FACTOR_WIDTH-1:0] w_r = w[2*FACTOR_WIDTH-1:FACTOR_WIDTH];
    wire signed [FACTOR_WIDTH-1:0] w_i = w[FACTOR_WIDTH-1:0];

    reg phase;
    reg signed [DATA_WIDTH-1:0] reg_x0_r, reg_x0_i;
    reg signed [DATA_WIDTH+FACTOR_WIDTH-1:0] p1, p2, p3, p4;
    reg signed [DATA_WIDTH-1:0] tw_r, tw_i;

    always @(posedge clk) begin
        if (rst) begin
            phase       <= 1'b0;
            reg_x0_r    <= {DATA_WIDTH{1'b0}};
            reg_x0_i    <= {DATA_WIDTH{1'b0}};
            p1          <= {(DATA_WIDTH+FACTOR_WIDTH){1'b0}};
            p2          <= {(DATA_WIDTH+FACTOR_WIDTH){1'b0}};
            p3          <= {(DATA_WIDTH+FACTOR_WIDTH){1'b0}};
            p4          <= {(DATA_WIDTH+FACTOR_WIDTH){1'b0}};
            tw_r        <= {DATA_WIDTH{1'b0}};
            tw_i        <= {DATA_WIDTH{1'b0}};
            out_x0      <= {(2*DATA_WIDTH){1'b0}};
            out_x1      <= {(2*DATA_WIDTH){1'b0}};
        end else begin
            if (!phase) begin
                reg_x0_r <= x0_r;
                reg_x0_i <= x0_i;
                p1       <= x1_r * w_r;
                p2       <= x1_i * w_i;
                p3       <= x1_r * w_i;
                p4       <= x1_i * w_r;
            end else begin
                tw_r <= p1[DATA_WIDTH+FRAC_BITS-1:FRAC_BITS] - p2[DATA_WIDTH+FRAC_BITS-1:FRAC_BITS];
                tw_i <= p3[DATA_WIDTH+FRAC_BITS-1:FRAC_BITS] + p4[DATA_WIDTH+FRAC_BITS-1:FRAC_BITS];

                out_x0[2*DATA_WIDTH-1:DATA_WIDTH] <= reg_x0_r + (p1[DATA_WIDTH+FRAC_BITS-1:FRAC_BITS] - p2[DATA_WIDTH+FRAC_BITS-1:FRAC_BITS]);
                out_x0[DATA_WIDTH-1:0]            <= reg_x0_i + (p3[DATA_WIDTH+FRAC_BITS-1:FRAC_BITS] + p4[DATA_WIDTH+FRAC_BITS-1:FRAC_BITS]);
                out_x1[2*DATA_WIDTH-1:DATA_WIDTH] <= reg_x0_r - (p1[DATA_WIDTH+FRAC_BITS-1:FRAC_BITS] - p2[DATA_WIDTH+FRAC_BITS-1:FRAC_BITS]);
                out_x1[DATA_WIDTH-1:0]            <= reg_x0_i - (p3[DATA_WIDTH+FRAC_BITS-1:FRAC_BITS] + p4[DATA_WIDTH+FRAC_BITS-1:FRAC_BITS]);
            end

            phase <= ~phase;
        end
    end
endmodule

Shared Butterfly FFT/Top_FFT/dual_port_ram.v
`timescale 1ns/1ps

module dual_port_ram #(
    parameter DATA_WIDTH = 32,
    parameter ADDR_WIDTH = 13
)(
    input  wire                   clk,
    input  wire                   wr_en,
    input  wire [ADDR_WIDTH-1:0]  wr_addr,
    input  wire [ADDR_WIDTH-1:0]  rd_addr,
    input  wire [DATA_WIDTH-1:0]  wr_in,
    output reg  [DATA_WIDTH-1:0]  rd_out
);
    (* ram_style = "block" *) reg [DATA_WIDTH-1:0] ram [0:(1<<ADDR_WIDTH)-1];

    always @(posedge clk) begin
        if (wr_en) begin
            ram[wr_addr] <= wr_in;
        end
    end

    always @(posedge clk) begin
        rd_out <= ram[rd_addr];
    end
endmodule

Shared Butterfly FFT/Top_FFT/butterfly_feeder.v
`timescale 1ns/1ps

module butterfly_feeder #(
    parameter DATA_WIDTH = 16
)(
    input  wire                      clk,
    input  wire                      rst,
    input  wire                      en,
    input  wire                      sel,
    input  wire [2*DATA_WIDTH-1:0]   ram_data,
    output reg  [2*DATA_WIDTH-1:0]   x0,
    output reg  [2*DATA_WIDTH-1:0]   x1,
    output wire                      pair_valid
);
    reg [2*DATA_WIDTH-1:0] x0_stage0;
    assign pair_valid = en && sel;

    always @(posedge clk) begin
        if (rst) begin
            x0_stage0  <= {(2*DATA_WIDTH){1'b0}};
            x0        <= {(2*DATA_WIDTH){1'b0}};
            x1        <= {(2*DATA_WIDTH){1'b0}};
        end else begin
            if (en) begin
                if (!sel) begin
                    x0_stage0 <= ram_data;
                end else begin
                    x0 <= x0_stage0;
                    x1 <= ram_data;
                end
            end
        end
    end
endmodule

Shared Butterfly FFT/Top_FFT/top_fft_dit_hold2.v
`timescale 1ns/1ps

module top_fft_dit_hold2 #(
    parameter N          = 16,
    parameter DATA_WIDTH = 16,
    parameter FRAC_BITS  = 14,
    parameter ADDR_WIDTH = $clog2(N)
)(
    input  wire                         clk,
    input  wire                         rst,
    input  wire                         en,
    input  wire [1:0]                   mode,
    input  wire signed [DATA_WIDTH-1:0] x_in_ext,

    output reg                          done,
    output reg  [3:0]                   state_dbg,
    output reg  [ADDR_WIDTH-1:0]        rd_addr_dbg,
    output reg  [ADDR_WIDTH-1:0]        wr_addr_dbg,
    output reg  [ADDR_WIDTH-1:0]        pair_idx_dbg,
    output wire [2*DATA_WIDTH-1:0]      x0_hold_dbg,
    output wire [2*DATA_WIDTH-1:0]      x1_hold_dbg,
    output wire [2*DATA_WIDTH-1:0]      y0_dbg,
    output wire [2*DATA_WIDTH-1:0]      y1_dbg
);
    localparam S_IDLE  = 4'd0;
    localparam S_LOAD  = 4'd1;
    localparam S_RD0   = 4'd2;
    localparam S_CAP   = 4'd3;
    localparam S_BF0   = 4'd6;
    localparam S_BF1   = 4'd7;
    localparam S_WR0   = 4'd8;
    localparam S_WR1   = 4'd9;
    localparam S_DONE  = 4'd10;

    reg [ADDR_WIDTH-1:0] load_idx;
    reg [ADDR_WIDTH-1:0] pair_idx;
    reg                  sample_phase;

    reg                   ram_wr_en;
    reg [ADDR_WIDTH-1:0]  ram_rd_addr;
    reg [ADDR_WIDTH-1:0]  ram_wr_addr;
    reg [2*DATA_WIDTH-1:0] ram_wr_in;
    wire [2*DATA_WIDTH-1:0] ram_rd_out;

    wire                   feeder_en;
    wire [2*DATA_WIDTH-1:0] x0_hold;
    wire [2*DATA_WIDTH-1:0] x1_hold;
    wire                    feeder_pair_valid;

    reg                    bfly_rst;
    wire [2*DATA_WIDTH-1:0] y0;
    wire [2*DATA_WIDTH-1:0] y1;

    localparam signed [DATA_WIDTH-1:0] W_ONE = (1 <<< FRAC_BITS);
    wire [2*DATA_WIDTH-1:0] w_const = {W_ONE, {DATA_WIDTH{1'b0}}};

    assign x0_hold_dbg = x0_hold;
    assign x1_hold_dbg = x1_hold;
    assign y0_dbg      = y0;
    assign y1_dbg      = y1;
    assign feeder_en   = (state_dbg == S_CAP);

    butterfly_feeder #(
        .DATA_WIDTH(DATA_WIDTH)
    ) feeder_i (
        .clk(clk),
        .rst(rst),
        .en(feeder_en),
        .sel(sample_phase),
        .ram_data(ram_rd_out),
        .x0(x0_hold),
        .x1(x1_hold),
        .pair_valid(feeder_pair_valid)
    );

    dual_port_ram #(
        .DATA_WIDTH(2*DATA_WIDTH),
        .ADDR_WIDTH(ADDR_WIDTH)
    ) mem_i (
        .clk(clk),
        .wr_en(ram_wr_en),
        .wr_addr(ram_wr_addr),
        .rd_addr(ram_rd_addr),
        .wr_in(ram_wr_in),
        .rd_out(ram_rd_out)
    );

    butterfly_dit #(
        .DATA_WIDTH(DATA_WIDTH),
        .FACTOR_WIDTH(DATA_WIDTH),
        .FRAC_BITS(FRAC_BITS)
    ) bfly_i (
        .clk(clk),
        .rst(bfly_rst),
        .in_x0(x0_hold),
        .in_x1(x1_hold),
        .w(w_const),
        .out_x0(y0),
        .out_x1(y1)
    );

    always @(posedge clk) begin
        if (rst) begin
            state_dbg    <= S_IDLE;
            done         <= 1'b0;
            load_idx     <= {ADDR_WIDTH{1'b0}};
            pair_idx     <= {ADDR_WIDTH{1'b0}};
            sample_phase <= 1'b0;
            ram_wr_en    <= 1'b0;
            ram_rd_addr  <= {ADDR_WIDTH{1'b0}};
            ram_wr_addr  <= {ADDR_WIDTH{1'b0}};
            ram_wr_in    <= {(2*DATA_WIDTH){1'b0}};
            bfly_rst     <= 1'b1;
            rd_addr_dbg  <= {ADDR_WIDTH{1'b0}};
            wr_addr_dbg  <= {ADDR_WIDTH{1'b0}};
            pair_idx_dbg <= {ADDR_WIDTH{1'b0}};
        end else begin
            ram_wr_en   <= 1'b0;
            bfly_rst    <= 1'b0;
            rd_addr_dbg <= ram_rd_addr;
            wr_addr_dbg <= ram_wr_addr;
            pair_idx_dbg <= pair_idx;

            case (state_dbg)
                S_IDLE: begin
                    done <= 1'b0;
                    if (en && mode == 2'b01) begin
                        load_idx  <= {ADDR_WIDTH{1'b0}};
                        state_dbg <= S_LOAD;
                    end
                end

                S_LOAD: begin
                    ram_wr_en   <= 1'b1;
                    ram_wr_addr <= load_idx;
                    ram_wr_in   <= {x_in_ext, {DATA_WIDTH{1'b0}}};
                    if (load_idx == N-1) begin
                        pair_idx    <= {ADDR_WIDTH{1'b0}};
                        sample_phase <= 1'b0;
                        state_dbg   <= S_RD0;
                    end else begin
                        load_idx <= load_idx + 1'b1;
                    end
                end

                S_RD0: begin
                    ram_rd_addr <= (pair_idx << 1) + sample_phase;
                    state_dbg   <= S_CAP;
                end

                S_CAP: begin
                    if (sample_phase) begin
                        sample_phase <= 1'b0;
                        if (feeder_pair_valid) begin
                            bfly_rst  <= 1'b1;
                            state_dbg <= S_BF0;
                        end else begin
                            state_dbg <= S_CAP;
                        end
                    end else begin
                        sample_phase <= 1'b1;
                        state_dbg    <= S_RD0;
                    end
                end

                S_BF0: begin
                    state_dbg <= S_BF1;
                end

                S_BF1: begin
                    state_dbg <= S_WR0;
                end

                S_WR0: begin
                    ram_wr_en   <= 1'b1;
                    ram_wr_addr <= pair_idx << 1;
                    ram_wr_in   <= y0;
                    state_dbg   <= S_WR1;
                end

                S_WR1: begin
                    ram_wr_en   <= 1'b1;
                    ram_wr_addr <= (pair_idx << 1) + 1'b1;
                    ram_wr_in   <= y1;
                    if (pair_idx == (N/2)-1) begin
                        state_dbg <= S_DONE;
                    end else begin
                        pair_idx  <= pair_idx + 1'b1;
                        state_dbg <= S_RD0;
                    end
                end

                S_DONE: begin
                    done <= 1'b1;
                    if (!en || mode == 2'b00) begin
                        state_dbg <= S_IDLE;
                    end
                end

                default: begin
                    state_dbg <= S_IDLE;
                end
            endcase
        end
    end
endmodule

Shared Butterfly FFT/Top_FFT/tb_top_fft_dit_hold2.v
`timescale 1ns/1ps

module tb_top_fft_dit_hold2;
    parameter N          = 16;
    parameter DATA_WIDTH = 16;
    parameter ADDR_WIDTH = $clog2(N);
    parameter CLK_PERIOD = 10;

    reg clk;
    reg rst;
    reg en;
    reg [1:0] mode;
    reg signed [DATA_WIDTH-1:0] x_in_ext;

    wire done;
    wire [3:0] state_dbg;
    wire [ADDR_WIDTH-1:0] rd_addr_dbg;
    wire [ADDR_WIDTH-1:0] wr_addr_dbg;
    wire [ADDR_WIDTH-1:0] pair_idx_dbg;
    wire [2*DATA_WIDTH-1:0] x0_hold_dbg;
    wire [2*DATA_WIDTH-1:0] x1_hold_dbg;
    wire [2*DATA_WIDTH-1:0] y0_dbg;
    wire [2*DATA_WIDTH-1:0] y1_dbg;

    localparam S_WR1 = 4'd9;

    top_fft_dit_hold2 #(
        .N(N),
        .DATA_WIDTH(DATA_WIDTH)
    ) uut (
        .clk(clk),
        .rst(rst),
        .en(en),
        .mode(mode),
        .x_in_ext(x_in_ext),
        .done(done),
        .state_dbg(state_dbg),
        .rd_addr_dbg(rd_addr_dbg),
        .wr_addr_dbg(wr_addr_dbg),
        .pair_idx_dbg(pair_idx_dbg),
        .x0_hold_dbg(x0_hold_dbg),
        .x1_hold_dbg(x1_hold_dbg),
        .y0_dbg(y0_dbg),
        .y1_dbg(y1_dbg)
    );

    always #(CLK_PERIOD/2) clk = ~clk;

    integer n;
    integer fd_pair;
    initial begin
        $dumpfile("tb_top_fft_dit_hold2.vcd");
        $dumpvars(0, tb_top_fft_dit_hold2);
    end

    initial begin
        clk = 1'b0;
        rst = 1'b1;
        en  = 1'b0;
        mode = 2'b00;
        x_in_ext = {DATA_WIDTH{1'b0}};

        fd_pair = $fopen("top_fft_pair_results.csv", "w");
        $fdisplay(fd_pair, "pair,y0_hex,y1_hex,y0_r,y0_i,y1_r,y1_i");

        #(5*CLK_PERIOD);
        rst  = 1'b0;
        en   = 1'b1;
        mode = 2'b01;

        for (n = 0; n < N; n = n + 1) begin
            x_in_ext = n;
            #(CLK_PERIOD);
        end

        wait(done == 1'b1);
        $display("Simulation done at t=%0t", $time);
        $fclose(fd_pair);
        #(5*CLK_PERIOD);
        $finish;
    end

    always @(posedge clk) begin
        $display("t=%0t state=%0d pair=%0d rd=%0d wr=%0d x0=%h x1=%h y0=%h y1=%h done=%b",
                 $time, state_dbg, pair_idx_dbg, rd_addr_dbg, wr_addr_dbg,
                 x0_hold_dbg, x1_hold_dbg, y0_dbg, y1_dbg, done);

        if (state_dbg == S_WR1) begin
            $fdisplay(fd_pair, "%0d,%08h,%08h,%0d,%0d,%0d,%0d",
                      pair_idx_dbg,
                      y0_dbg,
                      y1_dbg,
                      $signed(y0_dbg[2*DATA_WIDTH-1:DATA_WIDTH]),
                      $signed(y0_dbg[DATA_WIDTH-1:0]),
                      $signed(y1_dbg[2*DATA_WIDTH-1:DATA_WIDTH]),
                      $signed(y1_dbg[DATA_WIDTH-1:0]));
        end
    end

    initial begin
        #200000;
        $display("Timeout");
        $finish;
    end
endmodule

Shared Butterfly FFT/Top_FFT/tb_top_fft_dit_hold2.vcd
$date
	Sat Feb 14 12:00:36 2026
$end
$version
	Icarus Verilog
$end
$timescale
	1ps
$end
$scope module tb_top_fft_dit_hold2 $end
$var wire 32 ! y1_dbg [31:0] $end
$var wire 32 " y0_dbg [31:0] $end
$var wire 32 # x1_hold_dbg [31:0] $end
$var wire 32 $ x0_hold_dbg [31:0] $end
$var wire 4 % wr_addr_dbg [3:0] $end
$var wire 4 & state_dbg [3:0] $end
$var wire 4 ' rd_addr_dbg [3:0] $end
$var wire 4 ( pair_idx_dbg [3:0] $end
$var wire 1 ) done $end
$var parameter 32 * ADDR_WIDTH $end
$var parameter 32 + CLK_PERIOD $end
$var parameter 32 , DATA_WIDTH $end
$var parameter 32 - N $end
$var parameter 4 . S_WR1 $end
$var reg 1 / clk $end
$var reg 1 0 en $end
$var reg 2 1 mode [1:0] $end
$var reg 1 2 rst $end
$var reg 16 3 x_in_ext [15:0] $end
$var integer 32 4 fd_pair [31:0] $end
$var integer 32 5 n [31:0] $end
$scope module uut $end
$var wire 1 / clk $end
$var wire 1 0 en $end
$var wire 2 6 mode [1:0] $end
$var wire 1 2 rst $end
$var wire 32 7 w_const [31:0] $end
$var wire 32 8 x0_hold_dbg [31:0] $end
$var wire 32 9 x1_hold_dbg [31:0] $end
$var wire 16 : x_in_ext [15:0] $end
$var wire 32 ; y0_dbg [31:0] $end
$var wire 32 < y1_dbg [31:0] $end
$var wire 32 = y1 [31:0] $end
$var wire 32 > y0 [31:0] $end
$var wire 32 ? x1_hold [31:0] $end
$var wire 32 @ x0_hold [31:0] $end
$var wire 32 A ram_rd_out [31:0] $end
$var wire 1 B feeder_pair_valid $end
$var wire 1 C feeder_en $end
$var parameter 32 D ADDR_WIDTH $end
$var parameter 32 E DATA_WIDTH $end
$var parameter 32 F FRAC_BITS $end
$var parameter 32 G N $end
$var parameter 4 H S_BF0 $end
$var parameter 4 I S_BF1 $end
$var parameter 4 J S_CAP $end
$var parameter 4 K S_DONE $end
$var parameter 4 L S_IDLE $end
$var parameter 4 M S_LOAD $end
$var parameter 4 N S_RD0 $end
$var parameter 4 O S_WR0 $end
$var parameter 4 P S_WR1 $end
$var parameter 16 Q W_ONE $end
$var reg 1 R bfly_rst $end
$var reg 1 ) done $end
$var reg 4 S load_idx [3:0] $end
$var reg 4 T pair_idx [3:0] $end
$var reg 4 U pair_idx_dbg [3:0] $end
$var reg 4 V ram_rd_addr [3:0] $end
$var reg 4 W ram_wr_addr [3:0] $end
$var reg 1 X ram_wr_en $end
$var reg 32 Y ram_wr_in [31:0] $end
$var reg 4 Z rd_addr_dbg [3:0] $end
$var reg 1 [ sample_phase $end
$var reg 4 \ state_dbg [3:0] $end
$var reg 4 ] wr_addr_dbg [3:0] $end
$scope module bfly_i $end
$var wire 1 / clk $end
$var wire 1 R rst $end
$var wire 32 ^ w [31:0] $end
$var wire 16 _ x1_r [15:0] $end
$var wire 16 ` x1_i [15:0] $end
$var wire 16 a x0_r [15:0] $end
$var wire 16 b x0_i [15:0] $end
$var wire 16 c w_r [15:0] $end
$var wire 16 d w_i [15:0] $end
$var wire 32 e in_x1 [31:0] $end
$var wire 32 f in_x0 [31:0] $end
$var parameter 32 g DATA_WIDTH $end
$var parameter 32 h FACTOR_WIDTH $end
$var parameter 32 i FRAC_BITS $end
$var reg 32 j out_x0 [31:0] $end
$var reg 32 k out_x1 [31:0] $end
$var reg 32 l p1 [31:0] $end
$var reg 32 m p2 [31:0] $end
$var reg 32 n p3 [31:0] $end
$var reg 32 o p4 [31:0] $end
$var reg 1 p phase $end
$var reg 16 q reg_x0_i [15:0] $end
$var reg 16 r reg_x0_r [15:0] $end
$var reg 16 s tw_i [15:0] $end
$var reg 16 t tw_r [15:0] $end
$upscope $end
$scope module feeder_i $end
$var wire 1 / clk $end
$var wire 1 C en $end
$var wire 1 B pair_valid $end
$var wire 1 2 rst $end
$var wire 1 [ sel $end
$var wire 32 u ram_data [31:0] $end
$var parameter 32 v DATA_WIDTH $end
$var reg 32 w x0 [31:0] $end
$var reg 32 x x0_stage0 [31:0] $end
$var reg 32 y x1 [31:0] $end
$upscope $end
$scope module mem_i $end
$var wire 1 / clk $end
$var wire 4 z rd_addr [3:0] $end
$var wire 4 { wr_addr [3:0] $end
$var wire 1 X wr_en $end
$var wire 32 | wr_in [31:0] $end
$var parameter 32 } ADDR_WIDTH $end
$var parameter 64 ~ DATA_WIDTH $end
$var reg 32 !" rd_out [31:0] $end
$upscope $end
$upscope $end
$upscope $end
$enddefinitions $end
$comment Show the parameter values. $end
$dumpall
b100000 ~
b100 }
b10000 v
b1110 i
b10000 h
b10000 g
b100000000000000 Q
b1001 P
b1000 O
b10 N
b1 M
b0 L
b1010 K
b11 J
b111 I
b110 H
b10000 G
b1110 F
b10000 E
b100 D
b1001 .
b10000 -
b10000 ,
b1010 +
b100 *
$end
#0
$dumpvars
bx !"
bx |
bx {
bx z
bx y
bx x
bx w
bx u
bx t
bx s
bx r
bx q
xp
bx o
bx n
bx m
bx l
bx k
bx j
bx f
bx e
b0 d
b100000000000000 c
bx b
bx a
bx `
bx _
b1000000000000000000000000000000 ^
bx ]
bx \
x[
bx Z
bx Y
xX
bx W
bx V
bx U
bx T
bx S
xR
xC
xB
bx A
bx @
bx ?
bx >
bx =
bx <
bx ;
b0 :
bx 9
bx 8
b1000000000000000000000000000000 7
b0 6
bx 5
b10000000000000000000000000000011 4
b0 3
12
b0 1
00
0/
x)
bx (
bx '
bx &
bx %
bx $
bx #
bx "
bx !
$end
#5000
b0 `
b0 _
b0 b
b0 a
0B
b0 #
b0 9
b0 ?
b0 e
b0 y
b0 $
b0 8
b0 @
b0 f
b0 w
b0 x
b0 (
b0 U
b0 %
b0 ]
b0 '
b0 Z
1R
b0 Y
b0 |
b0 W
b0 {
b0 V
b0 z
0X
0[
b0 T
b0 S
0)
0C
b0 &
b0 \
1/
#10000
0/
#15000
b0 !
b0 <
b0 =
b0 k
b0 "
b0 ;
b0 >
b0 j
b0 s
b0 t
b0 o
b0 n
b0 m
b0 l
b0 q
b0 r
0p
1/
#20000
0/
#25000
1/
#30000
0/
#35000
1/
#40000
0/
#45000
1/
#50000
0/
b0 5
b1 1
b1 6
10
02
#55000
b1 &
b1 \
0R
1/
#60000
0/
b1 3
b1 :
b1 5
#65000
1p
b1 S
b10000000000000000 Y
b10000000000000000 |
1X
1/
#70000
0/
b10 3
b10 :
b10 5
#75000
b10 S
b100000000000000000 Y
b100000000000000000 |
b1 W
b1 {
1X
0p
1/
#80000
0/
b11 3
b11 :
b11 5
#85000
b10000000000000000 A
b10000000000000000 u
b10000000000000000 !"
1p
b11 S
b110000000000000000 Y
b110000000000000000 |
b10 W
b10 {
b1 %
b1 ]
1X
1/
#90000
0/
b100 3
b100 :
b100 5
#95000
b100 S
b1000000000000000000 Y
b1000000000000000000 |
b11 W
b11 {
b10 %
b10 ]
1X
0p
1/
#100000
0/
b101 3
b101 :
b101 5
#105000
1p
b101 S
b1010000000000000000 Y
b1010000000000000000 |
b100 W
b100 {
b11 %
b11 ]
1X
1/
#110000
0/
b110 3
b110 :
b110 5
#115000
b110 S
b1100000000000000000 Y
b1100000000000000000 |
b101 W
b101 {
b100 %
b100 ]
1X
0p
1/
#120000
0/
b111 3
b111 :
b111 5
#125000
1p
b111 S
b1110000000000000000 Y
b1110000000000000000 |
b110 W
b110 {
b101 %
b101 ]
1X
1/
#130000
0/
b1000 3
b1000 :
b1000 5
#135000
b1000 S
b10000000000000000000 Y
b10000000000000000000 |
b111 W
b111 {
b110 %
b110 ]
1X
0p
1/
#140000
0/
b1001 3
b1001 :
b1001 5
#145000
1p
b1001 S
b10010000000000000000 Y
b10010000000000000000 |
b1000 W
b1000 {
b111 %
b111 ]
1X
1/
#150000
0/
b1010 3
b1010 :
b1010 5
#155000
b1010 S
b10100000000000000000 Y
b10100000000000000000 |
b1001 W
b1001 {
b1000 %
b1000 ]
1X
0p
1/
#160000
0/
b1011 3
b1011 :
b1011 5
#165000
1p
b1011 S
b10110000000000000000 Y
b10110000000000000000 |
b1010 W
b1010 {
b1001 %
b1001 ]
1X
1/
#170000
0/
b1100 3
b1100 :
b1100 5
#175000
b1100 S
b11000000000000000000 Y
b11000000000000000000 |
b1011 W
b1011 {
b1010 %
b1010 ]
1X
0p
1/
#180000
0/
b1101 3
b1101 :
b1101 5
#185000
1p
b1101 S
b11010000000000000000 Y
b11010000000000000000 |
b1100 W
b1100 {
b1011 %
b1011 ]
1X
1/
#190000
0/
b1110 3
b1110 :
b1110 5
#195000
b1110 S
b11100000000000000000 Y
b11100000000000000000 |
b1101 W
b1101 {
b1100 %
b1100 ]
1X
0p
1/
#200000
0/
b1111 3
b1111 :
b1111 5
#205000
1p
b1111 S
b11110000000000000000 Y
b11110000000000000000 |
b1110 W
b1110 {
b1101 %
b1101 ]
1X
1/
#210000
0/
b10000 5
#215000
b10 &
b10 \
b1111 W
b1111 {
b1110 %
b1110 ]
1X
0p
1/
#220000
0/
#225000
1p
1C
b11 &
b11 \
b1111 %
b1111 ]
0X
1/
#230000
0/
#235000
0C
b10 &
b10 \
1[
0p
b10000000000000000 x
1/
#240000
0/
#245000
1B
1p
1C
b11 &
b11 \
b1 V
b1 z
1/
#250000
0/
#255000
0B
b1 _
b1 a
0C
b110 &
b110 \
1R
0[
b1 '
b1 Z
0p
b100000000000000000 A
b100000000000000000 u
b100000000000000000 !"
b10000000000000000 #
b10000000000000000 9
b10000000000000000 ?
b10000000000000000 e
b10000000000000000 y
b10000000000000000 $
b10000000000000000 8
b10000000000000000 @
b10000000000000000 f
b10000000000000000 w
1/
#260000
0/
#265000
b111 &
b111 \
0R
1/
#270000
0/
#275000
b1000 &
b1000 \
1p
b100000000000000 l
b1 r
1/
#280000
0/
#285000
0p
b100000000000000000 "
b100000000000000000 ;
b100000000000000000 >
b100000000000000000 j
b1 t
b1001 &
b1001 \
b0 Y
b0 |
b0 W
b0 {
1X
1/
#290000
0/
#295000
b10 &
b10 \
b1 T
b1 W
b1 {
b0 %
b0 ]
1X
1p
1/
#300000
0/
#305000
0p
1C
b11 &
b11 \
b10 V
b10 z
b1 (
b1 U
b1 %
b1 ]
0X
1/
#310000
0/
#315000
0C
b10 &
b10 \
1[
b10 '
b10 Z
1p
b110000000000000000 A
b110000000000000000 u
b110000000000000000 !"
b100000000000000000 x
1/
#320000
0/
#325000
1B
0p
1C
b11 &
b11 \
b11 V
b11 z
1/
#330000
0/
#335000
0B
b11 _
b10 a
0C
b110 &
b110 \
1R
0[
b11 '
b11 Z
1p
b1000000000000000000 A
b1000000000000000000 u
b1000000000000000000 !"
b110000000000000000 #
b110000000000000000 9
b110000000000000000 ?
b110000000000000000 e
b110000000000000000 y
b100000000000000000 $
b100000000000000000 8
b100000000000000000 @
b100000000000000000 f
b100000000000000000 w
1/
#340000
0/
#345000
b0 "
b0 ;
b0 >
b0 j
b0 t
b0 l
b0 r
0p
b111 &
b111 \
0R
1/
#350000
0/
#355000
b1000 &
b1000 \
1p
b1100000000000000 l
b10 r
1/
#360000
0/
#365000
0p
b11111111111111110000000000000000 !
b11111111111111110000000000000000 <
b11111111111111110000000000000000 =
b11111111111111110000000000000000 k
b1010000000000000000 "
b1010000000000000000 ;
b1010000000000000000 >
b1010000000000000000 j
b11 t
b1001 &
b1001 \
b10 W
b10 {
1X
1/
#370000
0/
#375000
b10 &
b10 \
b10 T
b11111111111111110000000000000000 Y
b11111111111111110000000000000000 |
b11 W
b11 {
b10 %
b10 ]
1X
1p
1/
#380000
0/
#385000
0p
1C
b11 &
b11 \
b100 V
b100 z
b10 (
b10 U
b11 %
b11 ]
0X
1/
#390000
0/
#395000
0C
b10 &
b10 \
1[
b100 '
b100 Z
1p
b1010000000000000000 A
b1010000000000000000 u
b1010000000000000000 !"
b1000000000000000000 x
1/
#400000
0/
#405000
1B
0p
1C
b11 &
b11 \
b101 V
b101 z
1/
#410000
0/
#415000
0B
b101 _
b100 a
0C
b110 &
b110 \
1R
0[
b101 '
b101 Z
1p
b1100000000000000000 A
b1100000000000000000 u
b1100000000000000000 !"
b1010000000000000000 #
b1010000000000000000 9
b1010000000000000000 ?
b1010000000000000000 e
b1010000000000000000 y
b1000000000000000000 $
b1000000000000000000 8
b1000000000000000000 @
b1000000000000000000 f
b1000000000000000000 w
1/
#420000
0/
#425000
b0 !
b0 <
b0 =
b0 k
b0 "
b0 ;
b0 >
b0 j
b0 t
b0 l
b0 r
0p
b111 &
b111 \
0R
1/
#430000
0/
#435000
b1000 &
b1000 \
1p
b10100000000000000 l
b100 r
1/
#440000
0/
#445000
0p
b11111111111111110000000000000000 !
b11111111111111110000000000000000 <
b11111111111111110000000000000000 =
b11111111111111110000000000000000 k
b10010000000000000000 "
b10010000000000000000 ;
b10010000000000000000 >
b10010000000000000000 j
b101 t
b1001 &
b1001 \
b0 Y
b0 |
b100 W
b100 {
1X
1/
#450000
0/
#455000
b10 &
b10 \
b11 T
b11111111111111110000000000000000 Y
b11111111111111110000000000000000 |
b101 W
b101 {
b100 %
b100 ]
1X
1p
1/
#460000
0/
#465000
0p
1C
b11 &
b11 \
b110 V
b110 z
b11 (
b11 U
b101 %
b101 ]
0X
1/
#470000
0/
#475000
0C
b10 &
b10 \
1[
b110 '
b110 Z
1p
b1110000000000000000 A
b1110000000000000000 u
b1110000000000000000 !"
b1100000000000000000 x
1/
#480000
0/
#485000
1B
0p
1C
b11 &
b11 \
b111 V
b111 z
1/
#490000
0/
#495000
0B
b111 _
b110 a
0C
b110 &
b110 \
1R
0[
b111 '
b111 Z
1p
b10000000000000000000 A
b10000000000000000000 u
b10000000000000000000 !"
b1110000000000000000 #
b1110000000000000000 9
b1110000000000000000 ?
b1110000000000000000 e
b1110000000000000000 y
b1100000000000000000 $
b1100000000000000000 8
b1100000000000000000 @
b1100000000000000000 f
b1100000000000000000 w
1/
#500000
0/
#505000
b0 !
b0 <
b0 =
b0 k
b0 "
b0 ;
b0 >
b0 j
b0 t
b0 l
b0 r
0p
b111 &
b111 \
0R
1/
#510000
0/
#515000
b1000 &
b1000 \
1p
b11100000000000000 l
b110 r
1/
#520000
0/
#525000
0p
b11111111111111110000000000000000 !
b11111111111111110000000000000000 <
b11111111111111110000000000000000 =
b11111111111111110000000000000000 k
b11010000000000000000 "
b11010000000000000000 ;
b11010000000000000000 >
b11010000000000000000 j
b111 t
b1001 &
b1001 \
b0 Y
b0 |
b110 W
b110 {
1X
1/
#530000
0/
#535000
b10 &
b10 \
b100 T
b11111111111111110000000000000000 Y
b11111111111111110000000000000000 |
b111 W
b111 {
b110 %
b110 ]
1X
1p
1/
#540000
0/
#545000
0p
1C
b11 &
b11 \
b1000 V
b1000 z
b100 (
b100 U
b111 %
b111 ]
0X
1/
#550000
0/
#555000
0C
b10 &
b10 \
1[
b1000 '
b1000 Z
1p
b10010000000000000000 A
b10010000000000000000 u
b10010000000000000000 !"
b10000000000000000000 x
1/
#560000
0/
#565000
1B
0p
1C
b11 &
b11 \
b1001 V
b1001 z
1/
#570000
0/
